python2somix/__init__.py
python2somix/python2somix.py
python2somix-0.1.1.dist-info/METADATA
python2somix-0.1.1.dist-info/WHEEL
python2somix-0.1.1.dist-info/licenses/LICENSE
python2somix-0.1.1.dist-info/RECORD
