Metadata-Version: 2.3
Name: python2somix
Version: 0.1.1
Summary: Extract SOMIX model from Python code
Project-URL: Homepage, https://github.com/Moose2Model/Python2SOMIX
Project-URL: Issues, https://github.com/Moose2Model/Python2SOMIX/issues
Author: Rainer W. Winkler
License-File: LICENSE
Classifier: License :: OSI Approved :: MIT License
Classifier: Operating System :: OS Independent
Classifier: Programming Language :: Python :: 3
Requires-Python: >=3.8
